{
    "/actions/default": "手部",
    "/actions/default/in/FingerCurlIndex": "食指弯曲",
    "/actions/default/in/FingerCurlMiddle": "中指弯曲",
    "/actions/default/in/FingerCurlPinky": "小指弯曲",
    "/actions/default/in/FingerCurlRing": "无名指弯曲",
    "/actions/default/in/FingerCurlThumb": "大拇指弯曲",
    "/actions/default/in/HandCurl": "手掌弯曲",
    "/actions/default/in/HandPoseLeft": "手势 (左)",
    "/actions/default/in/HandPoseRight": "手势 (右)",
    "/actions/default/in/HandSkeletonLeft": "骨骼 (左)",
    "/actions/default/in/HandSkeletonRight": "骨骼 (右)",
    "/actions/default/in/HapticVibration": "触觉振动",
    "/actions/default/in/TriggerPull": "扣动扳机",
    "/actions/dev": "菜单",
    "/actions/dev/in/MenuDismiss": "关闭菜单",
    "/actions/dev/in/MenuInteract": "菜单交互",
    "/actions/dev/in/ToggleMenu": "切换菜单",
    "/actions/scroll": "滚动",
    "/actions/scroll/in/Scroll": "滚动菜单",
    "/actions/scroll/in/ScrollTouchPad": "滚动菜单触控板",
    "/actions/interact": "交互",
    "/actions/interact/in/ArmGrenade": "触发手榴弹引信",
    "/actions/interact/in/ArmXenGrenade": "触发 Xen 手榴弹引信",
    "/actions/interact/in/GGLock": "重力手套锁定",
    "/actions/interact/in/HealthPen": "切换医疗笔",
    "/actions/interact/in/SqueezeXenGrenade": "按压 Xen 手榴弹",
    "/actions/interact/in/ToggleLaserSight": "切换激光瞄准器",
    "/actions/interact/in/Use": "使用",
    "/actions/interact/in/UseGrip": "使用握把",
    "/actions/move": "移动",
    "/actions/move/in/Teleport": "传送",
    "/actions/move/in/TeleportTurn": "轉向传送",
    "/actions/move/in/ContinuousTurn": "持续转向",
    "/actions/move/in/TurnLeft": "向左转",
    "/actions/move/in/TurnRight": "向右转",
    "/actions/move/in/MoveBack": "后退",
    "/actions/move/in/Walk": "行走",
    "/actions/move/in/ShiftDashJump": "跳跃",
    "/actions/move/in/WalkMantle": "攀爬",
    "/actions/move/in/MoveCrouchToggle": "蹲伏切换",
    "/actions/move/in/MoveStandToggle": "站立切换",
    "/actions/move/in/AdjustHeight": "调整高度",
    "/actions/weapon": "武器",
    "/actions/weapon/in/EjectClip": "弹出弹匣",
    "/actions/weapon/in/Fire": "射击",
    "/actions/weapon/in/AltFire": "次要武器射击",
    "/actions/weapon/in/OpenChamber": "打开枪膛",
    "/actions/weapon/in/ReleaseSlide": "释放滑轨",
    "/actions/weapon/in/Reload": "装弹",
    "/actions/weapon/in/ShowInventory": "显示物品栏",
    "/actions/weapon/in/ToggleBurstFire": "切换连发模式",
    "language_tag": "zh_CN"
}
